hs_django_admin/README.md
hs_django_admin/__init__.py
hs_django_admin/admin.py
hs_django_admin/apps.py
hs_django_admin/models.py
hs_django_admin/tests.py
hs_django_admin/views.py
hs_django_admin/migrations/0001_initial.py
hs_django_admin/migrations/__init__.py
hs_django_admin/static/.DS_Store
hs_django_admin/static/hs_django_admin/.DS_Store
hs_django_admin/static/hs_django_admin/css/custom.css
hs_django_admin/static/hs_django_admin/css/forms.css
hs_django_admin/static/hs_django_admin/images/.DS_Store
hs_django_admin/static/hs_django_admin/images/himosoft.png
hs_django_admin/static/hs_django_admin/js/theme.js
hs_django_admin/templates/admin/app_list.html
hs_django_admin/templates/admin/base.html
hs_django_admin/templates/admin/base_site.html
hs_django_admin/templates/admin/change_form.html
hs_django_admin/templates/admin/change_list.html
hs_django_admin/templates/admin/color_theme_toggle.html
hs_django_admin/templates/admin/hs_footer.html
hs_django_admin/templates/admin/index.html
hs_django_admin/templates/admin/nav_sidebar.html
hs_django_admin-1.0.0.dist-info/licenses/LICENSE
hs_django_admin-1.0.0.dist-info/METADATA
hs_django_admin-1.0.0.dist-info/WHEEL
hs_django_admin-1.0.0.dist-info/top_level.txt
hs_django_admin-1.0.0.dist-info/RECORD
