Metadata-Version: 2.4
Name: hs-django-admin
Version: 1.0.0
Summary: Customized Django admin panel with advanced UI and real-time system insights.
Home-page: https://github.com/Swe-HimelRana/hs-django-admin
Author: Himel
Author-email: Himosoft <contact@himosoft.com.bd>
Maintainer-email: Himel <contact@himelrana.com>
License: MIT
Project-URL: Homepage, https://github.com/Swe-HimelRana/hs-django-admin
Project-URL: Documentation, https://github.com/Swe-HImelRana/hs-django-admin#readme
Project-URL: Repository, https://github.com/Swe-HimelRana/hs-django-admin
Project-URL: Bug Tracker, https://github.com/Swe-HimelRana/hs-django-admin/issues
Keywords: django,admin,interface,customization,styling,custom django admin
Classifier: Development Status :: 4 - Beta
Classifier: Environment :: Web Environment
Classifier: Framework :: Django
Classifier: Framework :: Django :: 5.2
Classifier: Intended Audience :: Developers
Classifier: License :: OSI Approved :: MIT License
Classifier: Operating System :: OS Independent
Classifier: Programming Language :: Python
Classifier: Programming Language :: Python :: 3
Classifier: Programming Language :: Python :: 3.8
Classifier: Programming Language :: Python :: 3.9
Classifier: Programming Language :: Python :: 3.10
Classifier: Programming Language :: Python :: 3.11
Classifier: Programming Language :: Python :: 3.12
Classifier: Topic :: Internet :: WWW/HTTP
Classifier: Topic :: Internet :: WWW/HTTP :: Dynamic Content
Classifier: Topic :: Software Development :: Libraries :: Python Modules
Requires-Python: >=3.8
License-File: LICENSE
Requires-Dist: Django>=5.2
Provides-Extra: dev
Requires-Dist: twine>=4.0.0; extra == "dev"
Requires-Dist: build>=0.10.0; extra == "dev"
Requires-Dist: check-manifest>=0.48; extra == "dev"
Dynamic: author
Dynamic: home-page
Dynamic: license-file
Dynamic: requires-python
